Metadata-Version: 2.1
Name: django-find-apps
Version: 2020.7.1
Summary: find django apps
Home-page: https://github.com/andrewp-as-is/django-find-apps.py
License: Unlicense
Keywords: django apps
Platform: UNKNOWN
Classifier: Framework :: Django
Classifier: License :: Public Domain
Classifier: Operating System :: OS Independent
Classifier: Programming Language :: Python :: 3
